gdscript2rest/__init__.py
gdscript2rest/__main__.py
gdscript2rest/src/__init__.py
gdscript2rest/src/command_line.py
gdscript2rest/src/config.py
gdscript2rest/src/convert_to_restructured.py
gdscript2rest/src/gdscript_objects.py
gdscript2rest/src/make_restructured.py
gdscript2rest/src/utils.py
gdscript2rest-0.5.0.dist-info/LICENSE
gdscript2rest-0.5.0.dist-info/METADATA
gdscript2rest-0.5.0.dist-info/WHEEL
gdscript2rest-0.5.0.dist-info/top_level.txt
gdscript2rest-0.5.0.dist-info/RECORD
