Metadata-Version: 2.1
Name: gdscript2rest
Version: 0.5.0
Summary: Create API documentation in reStructuredText from Godot GDScript files
Home-page: https://github.com/DouglasWebster/gdscript-to-restructured
Author: Douglas Webster
Author-email: douglas.webster2107@gmail.com
License: { file="LICENSE"}
Project-URL: Bug Tracker, https://github.com/DouglasWebster/gdscript-to-restructured/issues
Keywords: godot,gdscript,documentation,restructured,sphinx
Classifier: Programming Language :: Python :: 3
Classifier: License :: OSI Approved :: MIT License
Classifier: Operating System :: OS Independent
Classifier: Development Status :: 4 - Beta
Requires-Python: >=3.6
License-File: LICENSE
Requires-Dist: ghapi
